{
  "_pattern": "02-missing-alt-text/informative-images",
  "_description": "Design tokens for the informative-images pattern. The accessibility fix is in HTML alt attributes, not color choices. These tokens document the page palette used in before/ and after/.",

  "color": {
    "text": {
      "primary": {
        "value": "#1a1a1a",
        "contrast-on-white": "18.1:1",
        "wcag": "AAA",
        "usage": "Body text, review headings"
      },
      "secondary": {
        "value": "#4a5568",
        "contrast-on-white": "5.74:1",
        "wcag": "AA",
        "usage": "Review metadata, chart axis labels"
      }
    },
    "brand": {
      "chart-primary": {
        "value": "#1d4ed8",
        "usage": "ProSound X1 bar in the battery-life chart, step circles in pairing diagram"
      },
      "chart-secondary": {
        "value": "#6b7280",
        "usage": "Competitor bars (Brand A, Brand B) in the battery-life chart"
      },
      "chart-success": {
        "value": "#16a34a",
        "usage": "Step 3 completion circle in the Bluetooth pairing diagram"
      }
    },
    "surface": {
      "page": {
        "value": "#ffffff",
        "usage": "Page background"
      },
      "product-bg": {
        "value": "#f8f9fa",
        "usage": "Background of the product photo illustration"
      },
      "card": {
        "value": "#ffffff",
        "usage": "Step card backgrounds in the pairing diagram"
      },
      "card-border": {
        "value": "#e2e8f0",
        "usage": "Step card borders and image borders"
      }
    }
  }
}
